elastic-objects/__init__.py
elastic-objects/elastic_object.py
elastic_objects/__init__.py
elastic_objects/elastic_object.py
liquidpy/__init__.py
liquidpy/liquid_object.py
elastic_objects-0.1.1.dist-info/LICENSE
elastic_objects-0.1.1.dist-info/METADATA
elastic_objects-0.1.1.dist-info/WHEEL
elastic_objects-0.1.1.dist-info/top_level.txt
elastic_objects-0.1.1.dist-info/RECORD
