Metadata-Version: 2.1
Name: elastic_objects
Version: 0.1.1
Summary: ElasticObjects introduces the concept of 'elastic objects' in Python - a flexible approach to object-oriented programming.
Home-page: https://github.com/paul-ot/elastic-objects
Author: Paul Marclay
Author-email: paul.eduardo.marclay@gmail.com
Classifier: Programming Language :: Python :: 3
Classifier: License :: OSI Approved :: MIT License
Classifier: Operating System :: OS Independent
Requires-Python: >=3.6
License-File: LICENSE
